{
  "entries": {
    "index.d2": {
      "version": 1,
      "grid": {
        "size": 16,
        "cols": 80,
        "rows": 114
      },
      "viewport": {
        "zoom": 1,
        "panX": 0,
        "panY": 0,
        "theme": "blueprint"
      },
      "settings": {
        "routing": {
          "shapeBuffer": 16,
          "leadOut": 16,
          "nudging": 16
        },
        "export": {
          "margin": 16,
          "showGrid": false
        }
      },
      "nodes": {
        "user": {
          "x": -480,
          "y": 352,
          "w": 80,
          "h": 80,
          "connections": {
            "top": [],
            "right": ["user->edge.cdn#0", "user->edge.lb#0"],
            "bottom": [],
            "left": []
          }
        },
        "edge": {
          "x": -48,
          "y": 288,
          "w": 352,
          "h": 160,
          "connections": {
            "top": [],
            "right": ["edge->api#0"],
            "bottom": [],
            "left": []
          }
        },
        "edge.cdn": {
          "x": 0,
          "y": 320,
          "w": 80,
          "h": 80,
          "connections": {
            "top": [],
            "right": [],
            "bottom": [],
            "left": ["user->edge.cdn#0"]
          }
        },
        "edge.lb": {
          "x": 96,
          "y": 320,
          "w": 160,
          "h": 80,
          "connections": {
            "top": [],
            "right": [],
            "bottom": ["user->edge.lb#0", "edge.lb->queue#0"],
            "left": []
          }
        },
        "api": {
          "x": 320,
          "y": 576,
          "w": 144,
          "h": 80,
          "connections": {
            "top": ["edge->api#0"],
            "right": [],
            "bottom": ["api->queue#0", "api->cache#0", "api->db#0"],
            "left": []
          }
        },
        "apib": {
          "x": 400,
          "y": 432,
          "w": 144,
          "h": 80,
          "connections": {
            "top": [],
            "right": [],
            "bottom": [],
            "left": []
          }
        },
        "worker": {
          "x": 0,
          "y": 896,
          "w": 192,
          "h": 96,
          "connections": {
            "top": ["queue->worker#0"],
            "right": [],
            "bottom": ["worker->db#0", "worker->cache#0"],
            "left": []
          }
        },
        "cache": {
          "x": 224,
          "y": 1392,
          "w": 96,
          "h": 80,
          "connections": {
            "top": ["worker->cache#0", "api->cache#0"],
            "right": [],
            "bottom": ["cache->db#0"],
            "left": []
          }
        },
        "db": {
          "x": 208,
          "y": 1632,
          "w": 128,
          "h": 128,
          "connections": {
            "top": ["worker->db#0", "cache->db#0", "api->db#0"],
            "right": [],
            "bottom": [],
            "left": []
          }
        },
        "queue": {
          "x": 0,
          "y": 752,
          "w": 192,
          "h": 64,
          "connections": {
            "top": ["edge.lb->queue#0", "api->queue#0"],
            "right": [],
            "bottom": ["queue->worker#0"],
            "left": []
          }
        }
      },
      "edges": {
        "user->edge.cdn#0": {
          "fromSide": "right",
          "toSide": "left"
        },
        "user->edge.lb#0": {
          "fromSide": "right",
          "toSide": "bottom"
        },
        "edge->api#0": {
          "fromSide": "right",
          "toSide": "top"
        },
        "api->cache#0": {
          "fromSide": "bottom",
          "toSide": "top"
        },
        "api->db#0": {
          "fromSide": "bottom",
          "toSide": "top"
        },
        "cache->db#0": {
          "fromSide": "bottom",
          "toSide": "top"
        },
        "api->queue#0": {
          "fromSide": "bottom",
          "toSide": "top"
        },
        "queue->worker#0": {
          "fromSide": "bottom",
          "toSide": "top"
        },
        "worker->db#0": {
          "fromSide": "bottom",
          "toSide": "top"
        },
        "worker->cache#0": {
          "fromSide": "bottom",
          "toSide": "top"
        },
        "edge.lb->queue#0": {
          "fromSide": "bottom",
          "toSide": "top"
        }
      },
      "unplaced": []
    }
  }
}
